botroyale/__init__.py
botroyale/default_settings.toml
botroyale/icon.ico
botroyale/icon.png
botroyale/api/__init__.py
botroyale/api/actions.py
botroyale/api/bots.py
botroyale/api/gui.py
botroyale/api/logging.py
botroyale/api/time_test.py
botroyale/assets/preview.gif
botroyale/assets/fonts/LICENCE.txt
botroyale/assets/fonts/firacode-mono-bold.ttf
botroyale/assets/fonts/firacode-mono.ttf
botroyale/assets/fonts/liberation-bold.ttf
botroyale/assets/fonts/liberation-mono-bold.ttf
botroyale/assets/fonts/liberation-mono.ttf
botroyale/assets/fonts/liberation.ttf
botroyale/assets/sprites/boat.png
botroyale/assets/sprites/bot.png
botroyale/assets/sprites/button_down.png
botroyale/assets/sprites/button_normal.png
botroyale/assets/sprites/ellipse.png
botroyale/assets/sprites/error.png
botroyale/assets/sprites/flower.png
botroyale/assets/sprites/fox.png
botroyale/assets/sprites/hex.png
botroyale/assets/sprites/penta.png
botroyale/assets/sprites/petals.png
botroyale/assets/sprites/pit.png
botroyale/assets/sprites/plate.png
botroyale/assets/sprites/plate_death_radius_trap.png
botroyale/assets/sprites/plate_pit_trap.png
botroyale/assets/sprites/plate_wall_trap.png
botroyale/assets/sprites/square.png
botroyale/assets/sprites/tree.png
botroyale/assets/sprites/wall.png
botroyale/assets/vfx/death.png
botroyale/assets/vfx/highlight.png
botroyale/assets/vfx/illegal.png
botroyale/assets/vfx/jump.png
botroyale/assets/vfx/kill.png
botroyale/assets/vfx/mark-blue.png
botroyale/assets/vfx/mark-green.png
botroyale/assets/vfx/mark-red.png
botroyale/assets/vfx/move.png
botroyale/assets/vfx/pressure-pop.png
botroyale/assets/vfx/push.png
botroyale/bots/__init__.py
botroyale/bots/basic.py
botroyale/bots/crazee_bot_003.py
botroyale/bots/crazee_bot_alpha.py
botroyale/bots/idle_bot.py
botroyale/bots/ninja_bot.py
botroyale/bots/random_bot.py
botroyale/gui/__init__.py
botroyale/gui/_defaults.py
botroyale/gui/app.py
botroyale/gui/menubar.py
botroyale/gui/battle/__init__.py
botroyale-0.1.4.dist-info/LICENSE
botroyale-0.1.4.dist-info/METADATA
botroyale-0.1.4.dist-info/WHEEL
botroyale-0.1.4.dist-info/entry_points.txt
botroyale-0.1.4.dist-info/top_level.txt
botroyale-0.1.4.dist-info/RECORD
