Metadata-Version: 2.1
Name: botroyale
Version: 0.1.4
Summary: A battle royale for bots.
Project-URL: Documentation, https://ariel.ninja/botroyale/docs
Project-URL: Source Code, https://github.com/ArielHorwitz/botroyale
Project-URL: Bug Tracker, https://github.com/ArielHorwitz/botroyale/issues
Classifier: License :: OSI Approved :: MIT License
Classifier: Development Status :: 3 - Alpha
Classifier: Operating System :: POSIX :: Linux
Classifier: Operating System :: Microsoft :: Windows
Classifier: Programming Language :: Python
Classifier: Programming Language :: Python :: 3
Classifier: Programming Language :: Python :: 3 :: Only
Classifier: Programming Language :: Python :: 3.9
Classifier: Programming Language :: Python :: 3.10
Classifier: Programming Language :: Python :: 3.11
Classifier: Natural Language :: English
Classifier: Intended Audience :: Developers
Classifier: Intended Audience :: Education
Classifier: Topic :: Games/Entertainment :: Turn Based Strategy
Classifier: Topic :: Scientific/Engineering :: Artificial Intelligence
Classifier: Typing :: Typed
Requires-Python: >=3.9
License-File: LICENSE
Requires-Dist: Kivy ==2.3.0
Requires-Dist: numpy ==2.0.2
Requires-Dist: tomlkit ==0.11.4
Provides-Extra: dev
Requires-Dist: pytest ==7.1.3 ; extra == 'dev'
Requires-Dist: hypothesis ==6.54.5 ; extra == 'dev'
Requires-Dist: black ==22.6.0 ; extra == 'dev'
Requires-Dist: flake8 ==5.0.4 ; extra == 'dev'
Requires-Dist: flake8-docstrings ==1.6.0 ; extra == 'dev'
Requires-Dist: pdoc3 ==0.10.0 ; extra == 'dev'
